emails/__init__.py
emails/_src.py
py_emails-1.2.0.dist-info/LICENSE
py_emails-1.2.0.dist-info/METADATA
py_emails-1.2.0.dist-info/WHEEL
py_emails-1.2.0.dist-info/top_level.txt
py_emails-1.2.0.dist-info/RECORD
