Metadata-Version: 2.1
Name: py-emails
Version: 1.2.0
Summary: Simple wrapper around email and smtplib for composing and sending email messages in an intuitive, simple interface.
Home-page: https://github.com/whitebarry/py-emails
Author: Barry Barrette
Author-email: barrybarrette@gmail.com
License: UNKNOWN
Platform: UNKNOWN
